Orange3_Prototypes-0.21.2-py3.11-nspkg.pth
Orange3_Prototypes-0.21.2.data/data/help/orange3-prototypes/.buildinfo
Orange3_Prototypes-0.21.2.data/data/help/orange3-prototypes/genindex.html
Orange3_Prototypes-0.21.2.data/data/help/orange3-prototypes/index.html
Orange3_Prototypes-0.21.2.data/data/help/orange3-prototypes/objects.inv
Orange3_Prototypes-0.21.2.data/data/help/orange3-prototypes/search.html
Orange3_Prototypes-0.21.2.data/data/help/orange3-prototypes/searchindex.js
Orange3_Prototypes-0.21.2.data/data/help/orange3-prototypes/_images/scoring-sheet-viewer-widget.png
Orange3_Prototypes-0.21.2.data/data/help/orange3-prototypes/_images/scoring-sheet-viewer-workflow.png
Orange3_Prototypes-0.21.2.data/data/help/orange3-prototypes/_images/scoring-sheet-widget.png
Orange3_Prototypes-0.21.2.data/data/help/orange3-prototypes/_images/scoring-sheet-workflow-2.png
Orange3_Prototypes-0.21.2.data/data/help/orange3-prototypes/_images/scoring-sheet-workflow.png
Orange3_Prototypes-0.21.2.data/data/help/orange3-prototypes/_sources/index.rst.txt
Orange3_Prototypes-0.21.2.data/data/help/orange3-prototypes/_sources/widgets/scoring-sheet-viewer.md.txt
Orange3_Prototypes-0.21.2.data/data/help/orange3-prototypes/_sources/widgets/scoring-sheet.md.txt
Orange3_Prototypes-0.21.2.data/data/help/orange3-prototypes/_static/_sphinx_javascript_frameworks_compat.js
Orange3_Prototypes-0.21.2.data/data/help/orange3-prototypes/_static/basic.css
Orange3_Prototypes-0.21.2.data/data/help/orange3-prototypes/_static/custom.css
Orange3_Prototypes-0.21.2.data/data/help/orange3-prototypes/_static/doctools.js
Orange3_Prototypes-0.21.2.data/data/help/orange3-prototypes/_static/documentation_options.js
Orange3_Prototypes-0.21.2.data/data/help/orange3-prototypes/_static/file.png
Orange3_Prototypes-0.21.2.data/data/help/orange3-prototypes/_static/jquery.js
Orange3_Prototypes-0.21.2.data/data/help/orange3-prototypes/_static/language_data.js
Orange3_Prototypes-0.21.2.dist-info/LICENSE
Orange3_Prototypes-0.21.2.dist-info/METADATA
Orange3_Prototypes-0.21.2.dist-info/WHEEL
Orange3_Prototypes-0.21.2.dist-info/entry_points.txt
Orange3_Prototypes-0.21.2.dist-info/namespace_packages.txt
Orange3_Prototypes-0.21.2.dist-info/top_level.txt
Orange3_Prototypes-0.21.2.dist-info/RECORD
